{
    "_max_retries": 5,
    "_timeout": 25,
    "date": "2012-12-15",
    "entries": [
        {
            "artist": "Rihanna",
            "image": null,
            "isNew": false,
            "lastPos": 1,
            "peakPos": 1,
            "rank": 1,
            "title": "Diamonds",
            "weeks": 10
        },
        {
            "artist": "Bruno Mars",
            "image": null,
            "isNew": false,
            "lastPos": 4,
            "peakPos": 2,
            "rank": 2,
            "title": "Locked Out Of Heaven",
            "weeks": 9
        },
        {
            "artist": "Ke$ha",
            "image": null,
            "isNew": false,
            "lastPos": 2,
            "peakPos": 2,
            "rank": 3,
            "title": "Die Young",
            "weeks": 10
        },
        {
            "artist": "Maroon 5",
            "image": null,
            "isNew": false,
            "lastPos": 3,
            "peakPos": 1,
            "rank": 4,
            "title": "One More Night",
            "weeks": 24
        },
        {
            "artist": "The Lumineers",
            "image": null,
            "isNew": false,
            "lastPos": 7,
            "peakPos": 5,
            "rank": 5,
            "title": "Ho Hey",
            "weeks": 26
        },
        {
            "artist": "fun.",
            "image": null,
            "isNew": false,
            "lastPos": 6,
            "peakPos": 3,
            "rank": 6,
            "title": "Some Nights",
            "weeks": 41
        },
        {
            "artist": "Phillip Phillips",
            "image": null,
            "isNew": false,
            "lastPos": 8,
            "peakPos": 7,
            "rank": 7,
            "title": "Home",
            "weeks": 23
        },
        {
            "artist": "Flo Rida",
            "image": null,
            "isNew": false,
            "lastPos": 9,
            "peakPos": 8,
            "rank": 8,
            "title": "I Cry",
            "weeks": 10
        },
        {
            "artist": "Ne-Yo",
            "image": null,
            "isNew": false,
            "lastPos": 10,
            "peakPos": 6,
            "rank": 9,
            "title": "Let Me Love You (Until You Learn To Love Yourself)",
            "weeks": 18
        },
        {
            "artist": "PSY",
            "image": null,
            "isNew": false,
            "lastPos": 5,
            "peakPos": 2,
            "rank": 10,
            "title": "Gangnam Style",
            "weeks": 13
        },
        {
            "artist": "Alicia Keys Featuring Nicki Minaj",
            "image": null,
            "isNew": false,
            "lastPos": 21,
            "peakPos": 11,
            "rank": 11,
            "title": "Girl On Fire",
            "weeks": 13
        },
        {
            "artist": "will.i.am & Britney Spears",
            "image": null,
            "isNew": true,
            "lastPos": 0,
            "peakPos": 12,
            "rank": 12,
            "title": "Scream & Shout",
            "weeks": 1
        },
        {
            "artist": "Alex Clare",
            "image": null,
            "isNew": false,
            "lastPos": 12,
            "peakPos": 7,
            "rank": 13,
            "title": "Too Close",
            "weeks": 36
        },
        {
            "artist": "Justin Bieber Featuring Nicki Minaj",
            "image": null,
            "isNew": false,
            "lastPos": 13,
            "peakPos": 13,
            "rank": 14,
            "title": "Beauty And A Beat",
            "weeks": 8
        },
        {
            "artist": "Taylor Swift",
            "image": null,
            "isNew": false,
            "lastPos": 11,
            "peakPos": 1,
            "rank": 15,
            "title": "We Are Never Ever Getting Back Together",
            "weeks": 17
        },
        {
            "artist": "Florida Georgia Line Featuring Nelly",
            "image": null,
            "isNew": false,
            "lastPos": 17,
            "peakPos": 16,
            "rank": 16,
            "title": "Cruise",
            "weeks": 16
        },
        {
            "artist": "Kendrick Lamar",
            "image": null,
            "isNew": false,
            "lastPos": 20,
            "peakPos": 17,
            "rank": 17,
            "title": "Swimming Pools (Drank)",
            "weeks": 16
        },
        {
            "artist": "Kanye West, Jay-Z, Big Sean",
            "image": null,
            "isNew": false,
            "lastPos": 16,
            "peakPos": 12,
            "rank": 18,
            "title": "Clique",
            "weeks": 13
        },
        {
            "artist": "Miguel",
            "image": null,
            "isNew": false,
            "lastPos": 19,
            "peakPos": 17,
            "rank": 19,
            "title": "Adorn",
            "weeks": 18
        },
        {
            "artist": "P!nk",
            "image": null,
            "isNew": false,
            "lastPos": 18,
            "peakPos": 18,
            "rank": 20,
            "title": "Try",
            "weeks": 6
        },
        {
            "artist": "Swedish House Mafia Featuring John Martin",
            "image": null,
            "isNew": false,
            "lastPos": 28,
            "peakPos": 21,
            "rank": 21,
            "title": "Don't You Worry Child",
            "weeks": 11
        },
        {
            "artist": "Chris Brown",
            "image": null,
            "isNew": false,
            "lastPos": 14,
            "peakPos": 10,
            "rank": 22,
            "title": "Don't Wake Me Up",
            "weeks": 23
        },
        {
            "artist": "Ed Sheeran",
            "image": null,
            "isNew": false,
            "lastPos": 23,
            "peakPos": 23,
            "rank": 23,
            "title": "The A Team",
            "weeks": 21
        },
        {
            "artist": "Nicki Minaj",
            "image": null,
            "isNew": false,
            "lastPos": 22,
            "peakPos": 22,
            "rank": 24,
            "title": "Va Va Voom",
            "weeks": 7
        },
        {
            "artist": "Imagine Dragons",
            "image": null,
            "isNew": false,
            "lastPos": 24,
            "peakPos": 22,
            "rank": 25,
            "title": "It's Time",
            "weeks": 26
        },
        {
            "artist": "Justin Bieber Featuring Big Sean",
            "image": null,
            "isNew": false,
            "lastPos": 15,
            "peakPos": 6,
            "rank": 26,
            "title": "As Long As You Love Me",
            "weeks": 24
        },
        {
            "artist": "50 Cent Featuring Eminem & Adam Levine",
            "image": null,
            "isNew": true,
            "lastPos": 0,
            "peakPos": 27,
            "rank": 27,
            "title": "My Life",
            "weeks": 1
        },
        {
            "artist": "Macklemore & Ryan Lewis Featuring Wanz",
            "image": null,
            "isNew": false,
            "lastPos": 35,
            "peakPos": 28,
            "rank": 28,
            "title": "Thrift Shop",
            "weeks": 9
        },
        {
            "artist": "Juicy J Featuring Lil Wayne & 2 Chainz",
            "image": null,
            "isNew": false,
            "lastPos": 31,
            "peakPos": 29,
            "rank": 29,
            "title": "Bandz A Make Her Dance",
            "weeks": 12
        },
        {
            "artist": "P!nk",
            "image": null,
            "isNew": false,
            "lastPos": 27,
            "peakPos": 5,
            "rank": 30,
            "title": "Blow Me (One Last Kiss)",
            "weeks": 22
        },
        {
            "artist": "Pitbull Featuring TJR",
            "image": null,
            "isNew": false,
            "lastPos": 30,
            "peakPos": 30,
            "rank": 31,
            "title": "Don't Stop The Party",
            "weeks": 7
        },
        {
            "artist": "Taylor Swift",
            "image": null,
            "isNew": false,
            "lastPos": 47,
            "peakPos": 3,
            "rank": 32,
            "title": "I Knew You Were Trouble.",
            "weeks": 7
        },
        {
            "artist": "Neon Trees",
            "image": null,
            "isNew": false,
            "lastPos": 26,
            "peakPos": 6,
            "rank": 33,
            "title": "Everybody Talks",
            "weeks": 38
        },
        {
            "artist": "Mumford & Sons",
            "image": null,
            "isNew": false,
            "lastPos": 36,
            "peakPos": 23,
            "rank": 34,
            "title": "I Will Wait",
            "weeks": 17
        },
        {
            "artist": "Frank Ocean",
            "image": null,
            "isNew": false,
            "lastPos": 37,
            "peakPos": 35,
            "rank": 35,
            "title": "Thinkin Bout You",
            "weeks": 21
        },
        {
            "artist": "OneRepublic",
            "image": null,
            "isNew": false,
            "lastPos": 38,
            "peakPos": 36,
            "rank": 36,
            "title": "Feel Again",
            "weeks": 14
        },
        {
            "artist": "Hunter Hayes",
            "image": null,
            "isNew": false,
            "lastPos": 40,
            "peakPos": 16,
            "rank": 37,
            "title": "Wanted",
            "weeks": 32
        },
        {
            "artist": "Ellie Goulding",
            "image": null,
            "isNew": false,
            "lastPos": 33,
            "peakPos": 2,
            "rank": 38,
            "title": "Lights",
            "weeks": 50
        },
        {
            "artist": "Owl City & Carly Rae Jepsen",
            "image": null,
            "isNew": false,
            "lastPos": 29,
            "peakPos": 8,
            "rank": 39,
            "title": "Good Time",
            "weeks": 23
        },
        {
            "artist": "The Script Featuring will.i.am",
            "image": null,
            "isNew": false,
            "lastPos": 46,
            "peakPos": 40,
            "rank": 40,
            "title": "Hall Of Fame",
            "weeks": 10
        },
        {
            "artist": "Carly Rae Jepsen",
            "image": null,
            "isNew": false,
            "lastPos": 34,
            "peakPos": 1,
            "rank": 41,
            "title": "Call Me Maybe",
            "weeks": 41
        },
        {
            "artist": "Lil Wayne Featuring Detail",
            "image": null,
            "isNew": false,
            "lastPos": 50,
            "peakPos": 42,
            "rank": 42,
            "title": "No Worries",
            "weeks": 13
        },
        {
            "artist": "Adele",
            "image": null,
            "isNew": false,
            "lastPos": 32,
            "peakPos": 8,
            "rank": 43,
            "title": "Skyfall",
            "weeks": 9
        },
        {
            "artist": "The Band Perry",
            "image": null,
            "isNew": false,
            "lastPos": 60,
            "peakPos": 44,
            "rank": 44,
            "title": "Better Dig Two",
            "weeks": 5
        },
        {
            "artist": "Of Monsters And Men",
            "image": null,
            "isNew": false,
            "lastPos": 49,
            "peakPos": 45,
            "rank": 45,
            "title": "Little Talks",
            "weeks": 28
        },
        {
            "artist": "French Montana Featuring Rick Ross, Drake, Lil Wayne",
            "image": null,
            "isNew": false,
            "lastPos": 45,
            "peakPos": 36,
            "rank": 46,
            "title": "Pop That",
            "weeks": 21
        },
        {
            "artist": "Gotye Featuring Kimbra",
            "image": null,
            "isNew": false,
            "lastPos": 43,
            "peakPos": 1,
            "rank": 47,
            "title": "Somebody That I Used To Know",
            "weeks": 48
        },
        {
            "artist": "Flo Rida",
            "image": null,
            "isNew": false,
            "lastPos": 41,
            "peakPos": 1,
            "rank": 48,
            "title": "Whistle",
            "weeks": 29
        },
        {
            "artist": "Carrie Underwood",
            "image": null,
            "isNew": false,
            "lastPos": 42,
            "peakPos": 20,
            "rank": 49,
            "title": "Blown Away",
            "weeks": 22
        },
        {
            "artist": "Luke Bryan",
            "image": null,
            "isNew": false,
            "lastPos": 39,
            "peakPos": 29,
            "rank": 50,
            "title": "Kiss Tomorrow Goodbye",
            "weeks": 15
        },
        {
            "artist": "Zac Brown Band",
            "image": null,
            "isNew": false,
            "lastPos": 59,
            "peakPos": 51,
            "rank": 51,
            "title": "Goodbye In Her Eyes",
            "weeks": 8
        },
        {
            "artist": "Justin Moore",
            "image": null,
            "isNew": false,
            "lastPos": 56,
            "peakPos": 52,
            "rank": 52,
            "title": "Til My Last Day",
            "weeks": 12
        },
        {
            "artist": "Kelly Clarkson",
            "image": null,
            "isNew": false,
            "lastPos": 57,
            "peakPos": 53,
            "rank": 53,
            "title": "Catch My Breath",
            "weeks": 6
        },
        {
            "artist": "Jake Owen",
            "image": null,
            "isNew": false,
            "lastPos": 51,
            "peakPos": 51,
            "rank": 54,
            "title": "The One That Got Away",
            "weeks": 17
        },
        {
            "artist": "Gary Allan",
            "image": null,
            "isNew": false,
            "lastPos": 63,
            "peakPos": 55,
            "rank": 55,
            "title": "Every Storm (Runs Out Of Rain)",
            "weeks": 9
        },
        {
            "artist": "Ellie Goulding",
            "image": null,
            "isNew": false,
            "lastPos": 64,
            "peakPos": 56,
            "rank": 56,
            "title": "Anything Could Happen",
            "weeks": 8
        },
        {
            "artist": "Kip Moore",
            "image": null,
            "isNew": false,
            "lastPos": 62,
            "peakPos": 57,
            "rank": 57,
            "title": "Beer Money",
            "weeks": 11
        },
        {
            "artist": "Calvin Harris Featuring Florence Welch",
            "image": null,
            "isNew": false,
            "lastPos": 82,
            "peakPos": 58,
            "rank": 58,
            "title": "Sweet Nothing",
            "weeks": 4
        },
        {
            "artist": "A$AP Rocky Featuring Drake, 2 Chainz & Kendrick Lamar",
            "image": null,
            "isNew": false,
            "lastPos": 66,
            "peakPos": 59,
            "rank": 59,
            "title": "F**kin Problems",
            "weeks": 5
        },
        {
            "artist": "2 Chainz Featuring Kanye West",
            "image": null,
            "isNew": false,
            "lastPos": 61,
            "peakPos": 47,
            "rank": 60,
            "title": "Birthday Song",
            "weeks": 17
        },
        {
            "artist": "Eric Church",
            "image": null,
            "isNew": false,
            "lastPos": 67,
            "peakPos": 61,
            "rank": 61,
            "title": "Creepin'",
            "weeks": 15
        },
        {
            "artist": "Rascal Flatts",
            "image": null,
            "isNew": false,
            "lastPos": 52,
            "peakPos": 52,
            "rank": 62,
            "title": "Come Wake Me Up",
            "weeks": 19
        },
        {
            "artist": "2 Chainz",
            "image": null,
            "isNew": false,
            "lastPos": 79,
            "peakPos": 63,
            "rank": 63,
            "title": "I'm Different",
            "weeks": 3
        },
        {
            "artist": "Randy Houser",
            "image": null,
            "isNew": false,
            "lastPos": 69,
            "peakPos": 64,
            "rank": 64,
            "title": "How Country Feels",
            "weeks": 9
        },
        {
            "artist": "Jason Aldean With Luke Bryan & Eric Church",
            "image": null,
            "isNew": false,
            "lastPos": 74,
            "peakPos": 65,
            "rank": 65,
            "title": "The Only Way I Know",
            "weeks": 4
        },
        {
            "artist": "Muse",
            "image": null,
            "isNew": false,
            "lastPos": 68,
            "peakPos": 60,
            "rank": 66,
            "title": "Madness",
            "weeks": 15
        },
        {
            "artist": "One Direction",
            "image": null,
            "isNew": false,
            "lastPos": 65,
            "peakPos": 41,
            "rank": 67,
            "title": "Little Things",
            "weeks": 3
        },
        {
            "artist": "Greg Bates",
            "image": null,
            "isNew": false,
            "lastPos": 70,
            "peakPos": 68,
            "rank": 68,
            "title": "Did It For The Girl",
            "weeks": 11
        },
        {
            "artist": "The Weeknd",
            "image": null,
            "isNew": false,
            "lastPos": 73,
            "peakPos": 69,
            "rank": 69,
            "title": "Wicked Games",
            "weeks": 5
        },
        {
            "artist": "One Direction",
            "image": null,
            "isNew": false,
            "lastPos": 55,
            "peakPos": 3,
            "rank": 70,
            "title": "Live While We're Young",
            "weeks": 9
        },
        {
            "artist": "Enrique Iglesias Featuring Sammy Adams",
            "image": null,
            "isNew": false,
            "lastPos": 54,
            "peakPos": 24,
            "rank": 71,
            "title": "Finally Found You",
            "weeks": 12
        },
        {
            "artist": "Imagine Dragons",
            "image": null,
            "isNew": false,
            "lastPos": 76,
            "peakPos": 71,
            "rank": 72,
            "title": "Radioactive",
            "weeks": 14
        },
        {
            "artist": "Brad Paisley",
            "image": null,
            "isNew": false,
            "lastPos": 75,
            "peakPos": 68,
            "rank": 73,
            "title": "Southern Comfort Zone",
            "weeks": 9
        },
        {
            "artist": "Kenny Chesney",
            "image": null,
            "isNew": false,
            "lastPos": 77,
            "peakPos": 74,
            "rank": 74,
            "title": "El Cerrito Place",
            "weeks": 8
        },
        {
            "artist": "T.I. Featuring Lil Wayne",
            "image": null,
            "isNew": false,
            "lastPos": 81,
            "peakPos": 50,
            "rank": 75,
            "title": "Ball",
            "weeks": 7
        },
        {
            "artist": "Rick Ross Featuring Wale & Drake",
            "image": null,
            "isNew": false,
            "lastPos": 80,
            "peakPos": 74,
            "rank": 76,
            "title": "Diced Pineapples",
            "weeks": 9
        },
        {
            "artist": "Taylor Swift",
            "image": null,
            "isNew": false,
            "lastPos": 78,
            "peakPos": 7,
            "rank": 77,
            "title": "Begin Again",
            "weeks": 9
        },
        {
            "artist": "Little Big Town",
            "image": null,
            "isNew": false,
            "lastPos": 83,
            "peakPos": 78,
            "rank": 78,
            "title": "Tornado",
            "weeks": 4
        },
        {
            "artist": "Miranda Lambert",
            "image": null,
            "isNew": false,
            "lastPos": 58,
            "peakPos": 47,
            "rank": 79,
            "title": "Fastest Girl In Town",
            "weeks": 19
        },
        {
            "artist": "Future",
            "image": null,
            "isNew": false,
            "lastPos": 72,
            "peakPos": 50,
            "rank": 80,
            "title": "Turn On The Lights",
            "weeks": 17
        },
        {
            "artist": "Chris Brown",
            "image": null,
            "isNew": false,
            "lastPos": 85,
            "peakPos": 81,
            "rank": 81,
            "title": "Don't Judge Me",
            "weeks": 5
        },
        {
            "artist": "Wiz Khalifa Featuring The Weeknd",
            "image": null,
            "isNew": false,
            "lastPos": 98,
            "peakPos": 82,
            "rank": 82,
            "title": "Remember You",
            "weeks": 2
        },
        {
            "artist": "Ludacris Featuring Usher & David Guetta",
            "image": null,
            "isNew": false,
            "lastPos": 0,
            "peakPos": 72,
            "rank": 83,
            "title": "Rest Of My Life",
            "weeks": 2
        },
        {
            "artist": "Kendrick Lamar Featuring Drake",
            "image": null,
            "isNew": false,
            "lastPos": 90,
            "peakPos": 76,
            "rank": 84,
            "title": "Poetic Justice",
            "weeks": 6
        },
        {
            "artist": "Jason Aldean",
            "image": null,
            "isNew": false,
            "lastPos": 84,
            "peakPos": 12,
            "rank": 85,
            "title": "Take A Little Ride",
            "weeks": 20
        },
        {
            "artist": "Hunter Hayes",
            "image": null,
            "isNew": false,
            "lastPos": 100,
            "peakPos": 86,
            "rank": 86,
            "title": "Somebody's Heartbreak",
            "weeks": 2
        },
        {
            "artist": "Bridgit Mendler",
            "image": null,
            "isNew": false,
            "lastPos": 87,
            "peakPos": 78,
            "rank": 87,
            "title": "Ready Or Not",
            "weeks": 7
        },
        {
            "artist": "Kelly Rowland Featuring Lil Wayne",
            "image": null,
            "isNew": false,
            "lastPos": 91,
            "peakPos": 88,
            "rank": 88,
            "title": "Ice",
            "weeks": 7
        },
        {
            "artist": "Meek Mill Featuring Kirko Bangz",
            "image": null,
            "isNew": false,
            "lastPos": 93,
            "peakPos": 89,
            "rank": 89,
            "title": "Young & Gettin' It",
            "weeks": 5
        },
        {
            "artist": "Game Featuring Chris Brown, Tyga, Wiz Khalifa & Lil Wayne",
            "image": null,
            "isNew": false,
            "lastPos": 96,
            "peakPos": 82,
            "rank": 90,
            "title": "Celebration",
            "weeks": 4
        },
        {
            "artist": "Dierks Bentley",
            "image": null,
            "isNew": false,
            "lastPos": 0,
            "peakPos": 91,
            "rank": 91,
            "title": "Tip It On Back",
            "weeks": 2
        },
        {
            "artist": "Beyonce",
            "image": null,
            "isNew": false,
            "lastPos": 92,
            "peakPos": 78,
            "rank": 92,
            "title": "Dance For You",
            "weeks": 13
        },
        {
            "artist": "Passion Pit",
            "image": null,
            "isNew": false,
            "lastPos": 99,
            "peakPos": 85,
            "rank": 93,
            "title": "Take A Walk",
            "weeks": 14
        },
        {
            "artist": "Melanie Martinez",
            "image": null,
            "isNew": true,
            "lastPos": 0,
            "peakPos": 94,
            "rank": 94,
            "title": "Too Close",
            "weeks": 1
        },
        {
            "artist": "Cassadee Pope",
            "image": null,
            "isNew": true,
            "lastPos": 0,
            "peakPos": 95,
            "rank": 95,
            "title": "Are You Happy Now?",
            "weeks": 1
        },
        {
            "artist": "Tim McGraw",
            "image": null,
            "isNew": true,
            "lastPos": 0,
            "peakPos": 96,
            "rank": 96,
            "title": "One Of Those Nights",
            "weeks": 1
        },
        {
            "artist": "Ludacris Featuring Kelly Rowland",
            "image": null,
            "isNew": true,
            "lastPos": 0,
            "peakPos": 97,
            "rank": 97,
            "title": "Representin'",
            "weeks": 1
        },
        {
            "artist": "Christina Perri Featuring Steve Kazee",
            "image": null,
            "isNew": false,
            "lastPos": 53,
            "peakPos": 53,
            "rank": 98,
            "title": "A Thousand Years (Part 2)",
            "weeks": 3
        },
        {
            "artist": "Cher Lloyd Featuring Becky G",
            "image": null,
            "isNew": true,
            "lastPos": 0,
            "peakPos": 99,
            "rank": 99,
            "title": "Oath",
            "weeks": 1
        },
        {
            "artist": "George Strait",
            "image": null,
            "isNew": false,
            "lastPos": 94,
            "peakPos": 94,
            "rank": 100,
            "title": "Give It All We Got Tonight",
            "weeks": 2
        }
    ],
    "name": "hot-100",
    "nextDate": "2012-12-22",
    "previousDate": "2012-12-08",
    "title": "The Hot 100",
    "year": null
}